obstacle/__init__.py
obstacle/common.py
obstacle/console.py
obstacle/demos.py
obstacle/tower.py
obstacle/unity.py
obstacle-0.1.0.dist-info/entry_points.txt
obstacle-0.1.0.dist-info/LICENSE
obstacle-0.1.0.dist-info/WHEEL
obstacle-0.1.0.dist-info/METADATA
obstacle-0.1.0.dist-info/RECORD
